annotation/__init__.py
annotation/annotate.py
annotation/bands.py
annotation/cli_main.py
annotation/ladder.py
annotation/utils.py
annotation/wells.py
annotation/assets/icon.ico
annotation/assets/icon.png
annotation/gui/gel_gui_wrapper.py
annotation/scripts/shortcuts.py
aer_gel_annotate-0.2.4.dist-info/METADATA
aer_gel_annotate-0.2.4.dist-info/WHEEL
aer_gel_annotate-0.2.4.dist-info/entry_points.txt
aer_gel_annotate-0.2.4.dist-info/top_level.txt
aer_gel_annotate-0.2.4.dist-info/RECORD
