Metadata-Version: 2.4
Name: aer-gel-annotate
Version: 0.2.4
Summary: GUI + pipeline for gel well detection, ladder reading, and PCR band annotation.
Author-email: Manan Shah <manan.b.shah@gmail.com>
License: MIT
Requires-Python: >=3.9
Requires-Dist: numpy>=1.24
Requires-Dist: scipy>=1.10
Requires-Dist: scikit-image>=0.22
Requires-Dist: matplotlib>=3.8
Requires-Dist: PyQt5>=5.15
Requires-Dist: tifffile>=2023.7.10
Requires-Dist: imagecodecs
Provides-Extra: windows
Requires-Dist: pywin32>=306; extra == "windows"
